growlog/__init__.py
growlog/__main__.py
growlog/cli.py
growlog/main.py
growlog-0.4.2.dist-info/METADATA
growlog-0.4.2.dist-info/RECORD
growlog-0.4.2.dist-info/WHEEL
growlog-0.4.2.dist-info/entry_points.txt
growlog-0.4.2.dist-info/top_level.txt
